ChangeLog
LICENSE
MANIFEST.in
README
setup.py
examples/dom.py
examples/infix.py
examples/ldom.py
html/MathDOM.html
html/codestyle.css
html/logo.png
html/project-support.png
mathdom.egg-info/PKG-INFO
mathdom.egg-info/top_level.txt
mathml/__init__.py
mathml/datatypes.py
mathml/lmathdom.py
mathml/mathdom.py
mathml/termbuilder.py
mathml/termparser.py
mathml/xmlterm.py
mathml/pmathml/__init__.py
mathml/pmathml/element.py
mathml/pmathml/entities.py
mathml/pmathml/events.py
mathml/pmathml/mfenced.py
mathml/pmathml/mfrac.py
mathml/pmathml/misc.py
mathml/pmathml/mmath.py
mathml/pmathml/mroot.py
mathml/pmathml/mrow.py
mathml/pmathml/mspace.py
mathml/pmathml/msubsup.py
mathml/pmathml/mtable.py
mathml/pmathml/mtoken.py
mathml/pmathml/munderover.py
mathml/pmathml/opdict.py
mathml/pmathml/opdict_data.py
mathml/pmathml/plotter.py
mathml/pmathml/backend/__init__.py
mathml/pmathml/backend/gdk_pango.py
mathml/pmathml/backend/nxplot_mathml.py
mathml/pmathml/backend/pangocairo_mathml.py
mathml/schema/__init__.py
mathml/schema/mathml2.rng.gz
mathml/utils/__init__.py
mathml/utils/ctop.xsl
mathml/utils/mathmlc2p.xsl
mathml/utils/pyterm.py
mathml/utils/sax_pmathml.py
mathml/utils/sqlterm.py
test/test.py
test/test_dom.py
