Metadata-Version: 1.0
Name: mathdom
Version: 0.7.1
Summary: MathDOM - Content MathML in Python
Home-page: http://mathdom.sourceforge.net/
Author: Stefan Behnel
Author-email: scoder@users.sourceforge.net
License: UNKNOWN
Download-URL: http://prdownloads.sourceforge.net/mathdom/mathdom-0.7.1.tar.gz?download
Keywords: MathML xml DOM math parser validator
Platform: UNKNOWN
Classifier: Development Status :: 5 - Production/Stable
Classifier: Intended Audience :: Developers
Classifier: Intended Audience :: Science/Research
Classifier: License :: OSI Approved :: MIT License
Classifier: Programming Language :: Python
Classifier: Topic :: Text Processing :: Markup :: XML
Classifier: Topic :: Scientific/Engineering :: Mathematics
Classifier: Topic :: Software Development :: Libraries :: Python Modules
